mycheats/__init__.py
mycheats/practs.py
mycheats/practicals/__init__.py
mycheats/practicals/bubble_sort.py
mycheats/practicals/singlylinkedlist.py
lalalanigga-0.1.1.dist-info/METADATA
lalalanigga-0.1.1.dist-info/WHEEL
lalalanigga-0.1.1.dist-info/top_level.txt
lalalanigga-0.1.1.dist-info/RECORD
