Metadata-Version: 2.4
Name: lalalanigga
Version: 0.1.1
Summary: A personal cheatsheet library for my DS practicals.
Author: Your Name
Dynamic: author
Dynamic: summary
